fastapi_walletauth/__init__.py
fastapi_walletauth/common.py
fastapi_walletauth/core.py
fastapi_walletauth/credentials.py
fastapi_walletauth/generate_keys.py
fastapi_walletauth/manager.py
fastapi_walletauth/middleware.py
fastapi_walletauth/router.py
fastapi_walletauth/transaction.py
fastapi_walletauth/verification.py
fastapi_walletauth-3.2.2.dist-info/METADATA
fastapi_walletauth-3.2.2.dist-info/WHEEL
fastapi_walletauth-3.2.2.dist-info/entry_points.txt
fastapi_walletauth-3.2.2.dist-info/RECORD
