Metadata-Version: 2.3
Name: fastapi-walletauth
Version: 3.2.2
Summary: FastAPI extension for user authentication through signature challenges
Keywords: FastAPI,authentication,signature,wallet,ethereum,solana,web3,jwt
Author: mhh
Author-email: mike.hukiewitz@robotter.ai
Requires-Python: >=3.9,<4.0
Classifier: Environment :: Web Environment
Classifier: License :: OSI Approved :: MIT License
Classifier: Operating System :: OS Independent
Classifier: Programming Language :: Python :: 3
Classifier: Programming Language :: Python :: 3.9
Classifier: Programming Language :: Python :: 3.10
Classifier: Programming Language :: Python :: 3.11
Classifier: Programming Language :: Python :: 3.12
Classifier: Programming Language :: Python :: 3.13
Classifier: Programming Language :: Python :: 3 :: Only
Classifier: Programming Language :: Python :: 3.6
Classifier: Programming Language :: Python :: 3.7
Classifier: Programming Language :: Python :: 3.8
Classifier: Topic :: Security
Classifier: Typing :: Typed
Requires-Dist: base58 (>=2.0.0,<3.0)
Requires-Dist: cryptography (>=41.0.3,<42.0.0)
Requires-Dist: eth-account (>=0.9.0,<0.10.0)
Requires-Dist: eth-keys (>=0.4.0,<0.5.0)
Requires-Dist: fastapi (>=0.100.0)
Requires-Dist: pydantic (>=2.0.0,<3.0.0)
Requires-Dist: pydantic-settings (>=2.7.1,<3.0.0)
Requires-Dist: pyjwt (>=2.8.0,<3.0.0)
Requires-Dist: pynacl (>=1.5.0,<2.0.0)
Requires-Dist: solders (>=0.26.0,<0.27.0)
